stock_clue/__init__.py
stock_clue/dartscrap/__init__.py
stock_clue/dartscrap/dart_scrap_dto.py
stock_clue/dartscrap/dividend_parser.py
stock_clue/dartscrap/facility_invest_parser.py
stock_clue/dartscrap/list_disclosure.py
stock_clue/dartscrap/preliminary_parser.py
stock_clue/dartscrap/revenue_volatility_parser.py
stock_clue/dartscrap/supply_agreement_parser.py
stock_clue/dartscrap/table_parser.py
stock_clue/error.py
stock_clue/opendart/__init__.py
stock_clue/opendart/base.py
stock_clue/opendart/base_dto.py
stock_clue/opendart/business_report_info.py
stock_clue/opendart/business_report_info_dto.py
stock_clue/opendart/disclosure.py
stock_clue/opendart/disclosure_dto.py
stock_clue/opendart/disclosure_type.py
stock_clue/opendart/financial_info.py
stock_clue/opendart/financial_info_dto.py
stock_clue/opendart/major_report.py
stock_clue/opendart/major_report_dto.py
stock_clue/opendart/request.py
stock_clue/opendart/utils.py
stock_clue-0.1.1.dist-info/LICENSE
stock_clue-0.1.1.dist-info/METADATA
stock_clue-0.1.1.dist-info/WHEEL
stock_clue-0.1.1.dist-info/RECORD
