Metadata-Version: 2.1
Name: stock-clue
Version: 0.1.1
Summary: 
Author: kgcrom
Author-email: kgcrom@hotmail.com
Requires-Python: >=3.8,<4.0
Classifier: Programming Language :: Python :: 3
Classifier: Programming Language :: Python :: 3.8
Classifier: Programming Language :: Python :: 3.9
Classifier: Programming Language :: Python :: 3.10
Classifier: Programming Language :: Python :: 3.11
Requires-Dist: beautifulsoup4 (>=4.12.2,<5.0.0)
Requires-Dist: pytest-playwright (>=0.4.3,<0.5.0)
Requires-Dist: requests (>=2.31.0,<3.0.0)
Requires-Dist: types-beautifulsoup4 (>=4.12.0.7,<5.0.0.0)
Requires-Dist: types-requests (>=2.31.0.10,<3.0.0.0)
Requires-Dist: xmlschema (>=2.5.0,<3.0.0)
